shiftcrypt-0.11.data/scripts/shiftcrypt
shiftcrypt_pkg/File.py
shiftcrypt_pkg/SaveFrame.py
shiftcrypt_pkg/TagTable.py
shiftcrypt_pkg/Text.py
shiftcrypt_pkg/Utils.py
shiftcrypt_pkg/__init__.py
shiftcrypt_pkg/autoenc_solo4.py
shiftcrypt_pkg/autoenchoder_standalone_version.py
shiftcrypt_pkg/base.py
shiftcrypt_pkg/chemical_shifts_custom_model.py
shiftcrypt_pkg/load_model.py
shiftcrypt_pkg/main_class.py
shiftcrypt_pkg/parser.py
shiftcrypt_pkg/readNef.py
shiftcrypt_pkg/shiftcrypt_cmd.py
shiftcrypt_pkg/utils.py
shiftcrypt_pkg/input_examples/bmr15315_1.nef
shiftcrypt_pkg/input_examples/bmr17160_1.nef
shiftcrypt_pkg/input_examples/bmr7339_1.nef
shiftcrypt_pkg/marshalled/new_NH.mtorch
shiftcrypt_pkg/marshalled/new_commons.mtorch
shiftcrypt_pkg/marshalled/new_full.mtorch
shiftcrypt-0.11.dist-info/METADATA
shiftcrypt-0.11.dist-info/WHEEL
shiftcrypt-0.11.dist-info/top_level.txt
shiftcrypt-0.11.dist-info/RECORD
