Metadata-Version: 2.1
Name: shiftcrypt
Version: 0.11
Summary: Auto-encoding NMR chemical shifts from their native vector space to a residue-level biophysical index
Home-page: https://bitbucket.org/grogdrinker/shiftcryp
Author: Gabriele Orlando
Author-email: orlando.gabriele89@gmail.com
License: UNKNOWN
Platform: UNKNOWN
Classifier: Programming Language :: Python :: 2
Classifier: License :: OSI Approved :: GNU Lesser General Public License v3 or later (LGPLv3+)
Classifier: Operating System :: OS Independent
Requires-Dist: numpy
Requires-Dist: scipy
Requires-Dist: sklearn
Requires-Dist: torch
Requires-Dist: torchvision
